[
  {
    "name": "about",
    "path": "/about",
    "component": "/Volumes/Extreme SSD/Websites/Bond&Co/bondandco/pages/about.vue",
    "chunkName": "pages/about"
  },
  {
    "name": "admin",
    "path": "/admin",
    "component": "/Volumes/Extreme SSD/Websites/Bond&Co/bondandco/pages/admin.vue",
    "chunkName": "pages/admin",
    "children": [
      {
        "name": "admin-services",
        "path": "services",
        "component": "/Volumes/Extreme SSD/Websites/Bond&Co/bondandco/pages/admin/services.vue",
        "chunkName": "pages/admin/services"
      }
    ]
  },
  {
    "name": "disclaimer",
    "path": "/disclaimer",
    "component": "/Volumes/Extreme SSD/Websites/Bond&Co/bondandco/pages/disclaimer.vue",
    "chunkName": "pages/disclaimer"
  },
  {
    "name": "login",
    "path": "/login",
    "component": "/Volumes/Extreme SSD/Websites/Bond&Co/bondandco/pages/login.vue",
    "chunkName": "pages/login"
  },
  {
    "name": "privacy_policy",
    "path": "/privacy_policy",
    "component": "/Volumes/Extreme SSD/Websites/Bond&Co/bondandco/pages/privacy_policy.vue",
    "chunkName": "pages/privacy_policy"
  },
  {
    "name": "services-slug",
    "path": "/services/:slug?",
    "component": "/Volumes/Extreme SSD/Websites/Bond&Co/bondandco/pages/services/_slug.vue",
    "chunkName": "pages/services/_slug"
  },
  {
    "name": "index",
    "path": "/",
    "component": "/Volumes/Extreme SSD/Websites/Bond&Co/bondandco/pages/index.vue",
    "chunkName": "pages/index"
  }
]
